.python-version
MANIFEST.in
Pipfile
Pipfile.lock
README.md
build.py
license.txt
meta.py
runTests.py
setup.py
simple_chalk/__init__.py
simple_chalk.egg-info/PKG-INFO
simple_chalk.egg-info/SOURCES.txt
simple_chalk.egg-info/dependency_links.txt
simple_chalk.egg-info/top_level.txt
simple_chalk/src/Style.py
simple_chalk/src/__init__.py
simple_chalk/src/data.py
simple_chalk/src/makeAChalkClass.py
simple_chalk/src/makeAChalkInstance.py
simple_chalk/src/makeChalkHelpers.py
simple_chalk/src/utils/__init__.py
simple_chalk/src/utils/append.py
simple_chalk/src/utils/appendAll.py
simple_chalk/src/utils/assignMissing.py
simple_chalk/src/utils/flatten.py
simple_chalk/src/utils/forEach.py
simple_chalk/src/utils/get.py
simple_chalk/src/utils/getAttributeKeys.py
simple_chalk/src/utils/invoke.py
simple_chalk/src/utils/invokeAttr.py
simple_chalk/src/utils/isEmpty.py
simple_chalk/src/utils/isLaden.py
simple_chalk/src/utils/isSomething.py
simple_chalk/src/utils/isTruthy.py
simple_chalk/src/utils/join.py
simple_chalk/src/utils/keepWhen.py
simple_chalk/src/utils/lowerFirst.py
simple_chalk/src/utils/mMap.py
simple_chalk/src/utils/map_.py
simple_chalk/src/utils/not_.py
simple_chalk/src/utils/passThrough.py
simple_chalk/src/utils/reduce.py
simple_chalk/src/utils/set_.py
simple_chalk/src/utils/startsWith.py
simple_chalk/src/utils/tee.py
simple_chalk/src/utils/throw.py
simple_chalk/src/utils/toString.py
simple_chalk/src/utils/upperFirst.py
simple_chalk/src/utils/whenTruthy.py
simple_chalk/src/utils/internal/__init__.py
simple_chalk/src/utils/internal/getFnSignature.py
simple_chalk/src/utils/internal/getNumPositionalParams.py
simple_chalk/src/utils/internal/getTypedResult.py
simple_chalk/src/utils/internal/makeCallFn.py
simple_chalk/src/utils/internal/validateStr.py
simple_chalk/tests/__init__.py
simple_chalk/tests/chainedStyles.py
simple_chalk/tests/colors.py
simple_chalk/tests/expectedErrors.py
simple_chalk/tests/miscStyles.py
simple_chalk/tests/utils.py