Metadata-Version: 2.1
Name: simple-chalk
Version: 0.1.0
Summary: A terminal string styling library
Home-page: https://github.com/olsonpm/py_simple-chalk
Author: phil
Author-email: philip.olson@pm.me
License: WTFNMFPL-1.0
Platform: UNKNOWN
Requires-Python: >=3.6
